cleanfill/__init__.py
cleanfill/fill.py
cleanfill-0.1.8.dist-info/LICENSE
cleanfill-0.1.8.dist-info/METADATA
cleanfill-0.1.8.dist-info/WHEEL
cleanfill-0.1.8.dist-info/top_level.txt
cleanfill-0.1.8.dist-info/RECORD
