Metadata-Version: 2.1
Name: cleanfill
Version: 0.1.8
Summary: It serve to fill NaN value in numpy array or in pandas dataframe using various prediction algorithmes.
Home-page: https://github.com/CryptoAdvised/cleanfill
Author: Colin Bouchard
Author-email: colin.bouchard.gestion@gmail.com
Classifier: Programming Language :: Python :: 3
Classifier: License :: OSI Approved :: MIT License
Classifier: Operating System :: OS Independent
Requires-Python: >=3.7
License-File: LICENSE
